xetrack/__init__.py
xetrack/assets.py
xetrack/bashplotlib.py
xetrack/cli.py
xetrack/config.py
xetrack/duckdb.py
xetrack/engine.py
xetrack/git.py
xetrack/logging.py
xetrack/reader.py
xetrack/stats.py
xetrack/tracker.py
xetrack-0.5.0.dist-info/LICENSE
xetrack-0.5.0.dist-info/METADATA
xetrack-0.5.0.dist-info/WHEEL
xetrack-0.5.0.dist-info/entry_points.txt
xetrack-0.5.0.dist-info/RECORD
