Metadata-Version: 2.1
Name: xetrack
Version: 0.5.0
Summary: A simple tool for benchamrking and tracking machine learning models and experiments.
License: MIT
Keywords: machine-learning,duckdb,pandas,sqlitedict,xxhash,loguru,monitoring,tracking,experimentation,benchmarking,data-science,data-analysis,data-visualization
Author: xdssio
Author-email: jonathan@xdss.io
Requires-Python: >=3.10,<4.0
Classifier: License :: OSI Approved :: MIT License
Classifier: Programming Language :: Python :: 3
Classifier: Programming Language :: Python :: 3.10
Classifier: Programming Language :: Python :: 3.11
Provides-Extra: assets
Provides-Extra: bashplotlib
Provides-Extra: cache
Provides-Extra: dev
Provides-Extra: duckdb
Requires-Dist: bashplotlib (>=0.6.0) ; extra == "dev" or extra == "bashplotlib"
Requires-Dist: cloudpickle (>=2.0.0)
Requires-Dist: coolname (>=2.2.0)
Requires-Dist: diskcache (>=5.6.0) ; extra == "dev" or extra == "cache"
Requires-Dist: duckdb (>=0.8.0) ; extra == "dev" or extra == "duckdb"
Requires-Dist: loguru (>=0.7.0)
Requires-Dist: numpy (>=1.26,<2.0)
Requires-Dist: pandas (>=2.0.3)
Requires-Dist: psutil (>=5.9.5)
Requires-Dist: sqlitedict (>=2.0.0) ; extra == "dev" or extra == "assets"
Requires-Dist: tabulate (>=0.9.0)
Requires-Dist: typer (>=0.9.0)
Requires-Dist: xxhash (>=3.4.1)
